setup.py
grpclb.egg-info/PKG-INFO
grpclb.egg-info/SOURCES.txt
grpclb.egg-info/dependency_links.txt
grpclb.egg-info/not-zip-safe
grpclb.egg-info/requires.txt
grpclb.egg-info/top_level.txt
grpclb_backend_v1/__init__.py
grpclb_backend_v1/backend_pb2.py
grpclb_backend_v1/backend_pb2_grpc.py
grpclb_balancer_v1/__init__.py
grpclb_balancer_v1/balancer_pb2.py
grpclb_balancer_v1/balancer_pb2_grpc.py