Metadata-Version: 1.1
Name: grpclb
Version: 0.3.1
Summary: grpclb contains automatically generated code for calling a grpclb server
Home-page: https://github.com/bsm/grpclb
Author: Black Square Media
Author-email: UNKNOWN
License: MIT
Platform: UNKNOWN
Classifier: Programming Language :: Python :: 3
Classifier: Programming Language :: Python :: 3.6
